{
  "coords": {
    "number": {
      "data": 0
    },
    "valid_time": {
      "data": [
        "2014-04-11T08:00:00",
        "2014-04-11T12:00:00",
        "2014-04-11T18:00:00"
      ]
    },
    "latitude": {
      "data": [
        51.55,
        51.3
      ]
    },
    "longitude": {
      "data": [
        -0.5,
        -0.25,
        0.0,
        0.25
      ]
    },
    "expver": {
      "data": [
        "0001",
        "0001",
        "0001"
      ]
    }
  },
  "data_vars": {
    "tp": {
      "data": [
        [
          [
            0.0,
            0.0,
            0.0,
            0.0
          ],
          [
            0.0,
            0.0,
            0.0,
            7.629423635080457e-07
          ]
        ],
        [
          [
            2.222023977083154e-05,
            3.433208985370584e-05,
            6.504059274448082e-05,
            4.920996798318811e-05
          ],
          [
            1.1634828297246713e-05,
            1.9741059077205136e-05,
            3.366433156770654e-05,
            4.377383811515756e-05
          ]
        ],
        [
          [
            0.0,
            0.0,
            0.0,
            0.0
          ],
          [
            0.0,
            0.0,
            0.0,
            3.8147118175402284e-07
          ]
        ]
      ]
    },
    "t2m": {
      "data": [
        [
          [
            283.24560546875,
            283.34912109375,
            283.46551513671875,
            283.54913330078125
          ],
          [
            283.44952392578125,
            283.49871826171875,
            283.5069580078125,
            283.4960021972656
          ]
        ],
        [
          [
            286.91790771484375,
            287.053466796875,
            287.346435546875,
            287.2347412109375
          ],
          [
            287.22613525390625,
            287.2894287109375,
            287.3390197753906,
            287.20306396484375
          ]
        ],
        [
          [
            286.7320556640625,
            286.78985595703125,
            287.02972412109375,
            286.36566162109375
          ],
          [
            286.9160461425781,
            286.85394287109375,
            286.8398742675781,
            286.3023681640625
          ]
        ]
      ]
    },
    "u10": {
      "data": [
        [
          [
            0.2930145859718323,
            0.20101934671401978,
            0.09809881448745728,
            0.059417784214019775
          ],
          [
            0.041061460971832275,
            -0.07652276754379272,
            -0.21128839254379272,
            -0.2792510390281677
          ]
        ],
        [
          [
            -0.14785760641098022,
            -0.12910455465316772,
            -0.17247003316879272,
            -0.4832152724266052
          ],
          [
            -0.7777404189109802,
            -0.7480620741844177,
            -0.7644652724266052,
            -0.9380950331687927
          ]
        ],
        [
          [
            0.747662365436554,
            0.675976574420929,
            0.49238282442092896,
            -0.31212157011032104
          ],
          [
            0.49882203340530396,
            0.46485596895217896,
            0.32911378145217896,
            -0.41874998807907104
          ]
        ]
      ]
    },
    "v10": {
      "data": [
        [
          [
            -3.002351760864258,
            -3.002939224243164,
            -3.035165786743164,
            -3.143564224243164
          ],
          [
            -3.3894596099853516,
            -3.3058643341064453,
            -3.181062698364258,
            -3.1916065216064453
          ]
        ],
        [
          [
            -2.569281578063965,
            -2.711676597595215,
            -2.8511266708374023,
            -2.92612361907959
          ],
          [
            -2.89585018157959,
            -2.992926597595215,
            -3.040778160095215,
            -3.13706111907959
          ]
        ],
        [
          [
            -0.9505224227905273,
            -1.1042394638061523,
            -1.2843084335327148,
            -0.9442663192749023
          ],
          [
            -1.5106725692749023,
            -1.6200475692749023,
            -1.6751317977905273,
            -1.0901708602905273
          ]
        ]
      ]
    },
    "sp": {
      "data": [
        [
          [
            101269.9453125,
            101313.7421875,
            101479.546875,
            101596.7421875
          ],
          [
            101306.34375,
            101270.34375,
            101181.1484375,
            101210.9453125
          ]
        ],
        [
          [
            101233.9140625,
            101279.3125,
            101444.9140625,
            101571.515625
          ],
          [
            101267.1171875,
            101233.9140625,
            101148.71875,
            101191.71875
          ]
        ],
        [
          [
            101166.0390625,
            101215.640625,
            101386.4375,
            101514.8359375
          ],
          [
            101210.640625,
            101181.4375,
            101099.640625,
            101142.8359375
          ]
        ]
      ]
    }
  },
  "pollution": {
    "pm25": 61,
    "pm10": 31,
    "o3": 27,
    "no2": 40,
    "so2": 4,
    "co": 7
  }
}