{
  "coords": {
    "number": {
      "data": 0
    },
    "valid_time": {
      "data": [
        "2015-01-17T08:00:00",
        "2015-01-17T12:00:00",
        "2015-01-17T18:00:00"
      ]
    },
    "latitude": {
      "data": [
        51.55,
        51.3
      ]
    },
    "longitude": {
      "data": [
        -0.5,
        -0.25,
        0.0,
        0.25
      ]
    },
    "expver": {
      "data": [
        "0001",
        "0001",
        "0001"
      ]
    }
  },
  "data_vars": {
    "tp": {
      "data": [
        [
          [
            0.0001823417842388153,
            0.00013990327715873718,
            1.9263476133346558e-05,
            1.2017786502838135e-05
          ],
          [
            5.846098065376282e-05,
            2.765655517578125e-05,
            0.0,
            0.0
          ]
        ],
        [
          [
            3.86237952625379e-05,
            0.0001777708384906873,
            0.00019101797079201788,
            0.00031022727489471436
          ],
          [
            0.00033035874366760254,
            0.000530436635017395,
            0.0006297081708908081,
            0.0004686415195465088
          ]
        ],
        [
          [
            0.0,
            0.0,
            0.0,
            0.0
          ],
          [
            0.0,
            0.0,
            0.0,
            0.0
          ]
        ]
      ]
    },
    "t2m": {
      "data": [
        [
          [
            272.8456115722656,
            272.4991455078125,
            272.0987548828125,
            272.25811767578125
          ],
          [
            272.5264892578125,
            272.21514892578125,
            271.8565673828125,
            271.7577209472656
          ]
        ],
        [
          [
            276.81744384765625,
            276.7362060546875,
            276.7674560546875,
            276.828369140625
          ],
          [
            277.3592529296875,
            277.2174377441406,
            277.07525634765625,
            277.10650634765625
          ]
        ],
        [
          [
            276.07037353515625,
            276.06842041015625,
            276.0766296386719,
            276.192626953125
          ],
          [
            276.2008361816406,
            276.2250671386719,
            276.2106018066406,
            276.3250732421875
          ]
        ]
      ]
    },
    "u10": {
      "data": [
        [
          [
            2.7110776901245117,
            2.6737852096557617,
            2.6083555221557617,
            2.7860898971557617
          ],
          [
            2.2450742721557617,
            2.2052183151245117,
            2.1802244186401367,
            2.3944883346557617
          ]
        ],
        [
          [
            3.0213375091552734,
            2.9764156341552734,
            2.998098373413086,
            2.910207748413086
          ],
          [
            3.2463436126708984,
            3.2162609100341797,
            3.262357711791992,
            3.043996810913086
          ]
        ],
        [
          [
            2.467742919921875,
            2.415008544921875,
            2.318328857421875,
            2.6208648681640625
          ],
          [
            2.0661773681640625,
            2.04547119140625,
            2.103485107421875,
            2.329071044921875
          ]
        ]
      ]
    },
    "v10": {
      "data": [
        [
          [
            3.8283042907714844,
            3.687877655029297,
            3.4863243103027344,
            3.364055633544922
          ],
          [
            3.2802696228027344,
            3.183971405029297,
            3.082805633544922,
            2.9497947692871094
          ]
        ],
        [
          [
            3.3548240661621094,
            3.537639617919922,
            3.6858787536621094,
            3.893108367919922
          ],
          [
            3.293498992919922,
            3.443309783935547,
            3.5345115661621094,
            3.637248992919922
          ]
        ],
        [
          [
            2.276508331298828,
            2.2372474670410156,
            2.0960350036621094,
            2.049549102783203
          ],
          [
            1.9888114929199219,
            1.9936943054199219,
            1.9788475036621094,
            2.0042381286621094
          ]
        ]
      ]
    },
    "sp": {
      "data": [
        [
          [
            100364.859375,
            100431.453125,
            100621.65625,
            100759.453125
          ],
          [
            100463.0546875,
            100448.2578125,
            100379.0546875,
            100428.859375
          ]
        ],
        [
          [
            100265.5859375,
            100331.78125,
            100519.3828125,
            100659.984375
          ],
          [
            100356.5859375,
            100343.5859375,
            100277.984375,
            100328.3828125
          ]
        ],
        [
          [
            100166.1875,
            100225.5859375,
            100409.1875,
            100542.7890625
          ],
          [
            100245.7890625,
            100226.5859375,
            100154.5859375,
            100200.390625
          ]
        ]
      ]
    }
  },
  "pollution": {
    "pm25": 47,
    "pm10": 16,
    "o3": 13,
    "no2": 26,
    "so2": 3,
    "co": 9
  }
}