{
  "coords": {
    "number": {
      "data": 0
    },
    "valid_time": {
      "data": [
        "2017-05-22T08:00:00",
        "2017-05-22T12:00:00",
        "2017-05-22T18:00:00"
      ]
    },
    "latitude": {
      "data": [
        51.55,
        51.3
      ]
    },
    "longitude": {
      "data": [
        -0.5,
        -0.25,
        0.0,
        0.25
      ]
    },
    "expver": {
      "data": [
        "0001",
        "0001",
        "0001"
      ]
    }
  },
  "data_vars": {
    "tp": {
      "data": [
        [
          [
            0.0,
            1.7166021279990673e-06,
            2.86102294921875e-06,
            1.7166021279990673e-06
          ],
          [
            0.0,
            0.0,
            0.0,
            0.0
          ]
        ],
        [
          [
            0.0,
            0.0,
            0.0,
            0.0
          ],
          [
            0.0,
            0.0,
            0.0,
            0.0
          ]
        ],
        [
          [
            0.0,
            0.0,
            0.0,
            0.0
          ],
          [
            0.0,
            0.0,
            0.0,
            0.0
          ]
        ]
      ]
    },
    "t2m": {
      "data": [
        [
          [
            289.0390625,
            289.2242431640625,
            289.62738037109375,
            289.6304931640625
          ],
          [
            289.3984375,
            289.49102783203125,
            289.56915283203125,
            289.6125183105469
          ]
        ],
        [
          [
            295.0987243652344,
            295.18426513671875,
            295.48779296875,
            294.79913330078125
          ],
          [
            295.17724609375,
            295.21551513671875,
            295.2694396972656,
            294.90106201171875
          ]
        ],
        [
          [
            293.96673583984375,
            294.1530456542969,
            294.53314208984375,
            294.4014892578125
          ],
          [
            293.1764831542969,
            293.3389892578125,
            293.6108703613281,
            293.7319641113281
          ]
        ]
      ]
    },
    "u10": {
      "data": [
        [
          [
            -2.4158935546875,
            -2.2426528930664062,
            -2.1018295288085938,
            -2.2387466430664062
          ],
          [
            -2.5428466796875,
            -2.3408966064453125,
            -2.1756591796875,
            -2.1133575439453125
          ]
        ],
        [
          [
            -1.3935365676879883,
            -1.0558443069458008,
            -0.7392396926879883,
            -1.2435426712036133
          ],
          [
            -1.4677553176879883,
            -1.1058473587036133,
            -0.8304567337036133,
            -0.9706850051879883
          ]
        ],
        [
          [
            1.246694803237915,
            1.12734055519104,
            0.875601053237915,
            0.18926072120666504
          ],
          [
            1.23750901222229,
            1.21425461769104,
            1.131826639175415,
            0.768362283706665
          ]
        ]
      ]
    },
    "v10": {
      "data": [
        [
          [
            2.30757999420166,
            2.11812686920166,
            1.8919610977172852,
            1.7929315567016602
          ],
          [
            2.338250160217285,
            2.1417627334594727,
            1.9339532852172852,
            1.8603143692016602
          ]
        ],
        [
          [
            3.8602447509765625,
            3.725677490234375,
            3.56219482421875,
            3.09051513671875
          ],
          [
            3.7733306884765625,
            3.64422607421875,
            3.48895263671875,
            3.3397369384765625
          ]
        ],
        [
          [
            3.44716739654541,
            3.1954126358032227,
            2.706536293029785,
            2.4547815322875977
          ],
          [
            3.3092737197875977,
            3.0920801162719727,
            2.783684730529785,
            2.6247034072875977
          ]
        ]
      ]
    },
    "sp": {
      "data": [
        [
          [
            100781.46875,
            100853.8671875,
            101041.8671875,
            101179.2734375
          ],
          [
            100814.46875,
            100809.875,
            100753.0703125,
            100806.0703125
          ]
        ],
        [
          [
            100648.15625,
            100717.5546875,
            100900.5546875,
            101040.953125
          ],
          [
            100696.15625,
            100688.5546875,
            100627.5546875,
            100679.5546875
          ]
        ],
        [
          [
            100484.0234375,
            100540.0234375,
            100711.2265625,
            100843.2265625
          ],
          [
            100554.421875,
            100532.828125,
            100459.0234375,
            100502.0234375
          ]
        ]
      ]
    }
  },
  "pollution": {
    "pm25": 72,
    "pm10": 23,
    "o3": 21,
    "no2": 47,
    "so2": 3,
    "co": 6
  }
}