{
  "coords": {
    "number": {
      "data": 0
    },
    "valid_time": {
      "data": [
        "2017-12-18T08:00:00",
        "2017-12-18T12:00:00",
        "2017-12-18T18:00:00"
      ]
    },
    "latitude": {
      "data": [
        51.55,
        51.3
      ]
    },
    "longitude": {
      "data": [
        -0.5,
        -0.25,
        0.0,
        0.25
      ]
    },
    "expver": {
      "data": [
        "0001",
        "0001",
        "0001"
      ]
    }
  },
  "data_vars": {
    "tp": {
      "data": [
        [
          [
            0.0,
            0.0,
            0.0,
            0.0
          ],
          [
            0.0,
            0.0,
            0.0,
            0.0
          ]
        ],
        [
          [
            0.0,
            0.0,
            0.0,
            0.0
          ],
          [
            0.0,
            0.0,
            0.0,
            0.0
          ]
        ],
        [
          [
            0.0,
            0.0,
            0.0,
            0.0
          ],
          [
            0.0,
            0.0,
            0.0,
            0.0
          ]
        ]
      ]
    },
    "t2m": {
      "data": [
        [
          [
            274.2986755371094,
            274.2369384765625,
            274.176025390625,
            274.46624755859375
          ],
          [
            274.02642822265625,
            273.97369384765625,
            273.96197509765625,
            274.2056884765625
          ]
        ],
        [
          [
            278.5533447265625,
            278.40997314453125,
            278.3677978515625,
            278.34747314453125
          ],
          [
            278.6310729980469,
            278.44708251953125,
            278.30804443359375,
            278.2958984375
          ]
        ],
        [
          [
            274.3533630371094,
            274.3600158691406,
            274.28619384765625,
            274.795166015625
          ],
          [
            273.78619384765625,
            273.8240661621094,
            273.9986877441406,
            274.5350036621094
          ]
        ]
      ]
    },
    "u10": {
      "data": [
        [
          [
            0.9933716058731079,
            0.9750152826309204,
            1.0189605951309204,
            1.3093963861465454
          ],
          [
            0.7773681879043579,
            0.7232605218887329,
            0.7506042718887329,
            1.076196312904358
          ]
        ],
        [
          [
            0.2636810541152954,
            0.4339996576309204,
            0.6753937005996704,
            1.1066375970840454
          ],
          [
            0.10605776309967041,
            0.2457062005996704,
            0.4289032220840454,
            0.8724762201309204
          ]
        ],
        [
          [
            1.7865228652954102,
            1.8101587295532227,
            1.9539117813110352,
            1.5771417617797852
          ],
          [
            1.1957025527954102,
            1.2146539688110352,
            1.3562555313110352,
            1.3240289688110352
          ]
        ]
      ]
    },
    "v10": {
      "data": [
        [
          [
            -2.7197418212890625,
            -2.7142791748046875,
            -2.5748214721679688,
            -2.8398590087890625
          ],
          [
            -2.5433807373046875,
            -2.5494308471679688,
            -2.622283935546875,
            -2.886932373046875
          ]
        ],
        [
          [
            -1.7794256210327148,
            -1.8950567245483398,
            -1.9968175888061523,
            -2.2430944442749023
          ],
          [
            -2.0202550888061523,
            -2.096808433532715,
            -2.19095516204834,
            -2.3704442977905273
          ]
        ],
        [
          [
            -1.5848455429077148,
            -1.7959814071655273,
            -1.9194097518920898,
            -1.5705938339233398
          ],
          [
            -1.9756689071655273,
            -2.1123876571655273,
            -2.225470542907715,
            -1.8838720321655273
          ]
        ]
      ]
    },
    "sp": {
      "data": [
        [
          [
            101781.2734375,
            101823.671875,
            101991.0703125,
            102106.2734375
          ],
          [
            101823.46875,
            101785.671875,
            101693.671875,
            101720.671875
          ]
        ],
        [
          [
            102043.53125,
            102087.1328125,
            102254.7265625,
            102368.9296875
          ],
          [
            102083.328125,
            102046.53125,
            101955.328125,
            101982.1328125
          ]
        ],
        [
          [
            102230.25,
            102280.8515625,
            102456.25,
            102582.6484375
          ],
          [
            102286.6484375,
            102256.8515625,
            102173.6484375,
            102210.046875
          ]
        ]
      ]
    }
  },
  "pollution": {
    "pm25": 76,
    "pm10": 46,
    "o3": 2,
    "no2": 56,
    "so2": 20,
    "co": 9
  }
}