{
  "coords": {
    "number": {
      "data": 0
    },
    "valid_time": {
      "data": [
        "2018-09-09T08:00:00",
        "2018-09-09T12:00:00",
        "2018-09-09T18:00:00"
      ]
    },
    "latitude": {
      "data": [
        51.55,
        51.3
      ]
    },
    "longitude": {
      "data": [
        -0.5,
        -0.25,
        0.0,
        0.25
      ]
    },
    "expver": {
      "data": [
        "0001",
        "0001",
        "0001"
      ]
    }
  },
  "data_vars": {
    "tp": {
      "data": [
        [
          [
            0.0,
            0.0,
            0.0,
            0.0
          ],
          [
            0.0,
            0.0,
            0.0,
            0.0
          ]
        ],
        [
          [
            8.459165837848559e-05,
            7.610358443344012e-05,
            6.074980046832934e-05,
            2.384148865530733e-05
          ],
          [
            8.554533269489184e-05,
            5.760193016612902e-05,
            1.144372254202608e-05,
            2.7656587917590514e-06
          ]
        ],
        [
          [
            0.0,
            0.0,
            0.0,
            0.0
          ],
          [
            0.0,
            0.0,
            0.0,
            0.0
          ]
        ]
      ]
    },
    "t2m": {
      "data": [
        [
          [
            289.1488952636719,
            289.0668640136719,
            289.05670166015625,
            289.059814453125
          ],
          [
            289.618408203125,
            289.4754638671875,
            289.3074951171875,
            289.2098388671875
          ]
        ],
        [
          [
            293.26513671875,
            293.3291931152344,
            293.54833984375,
            293.6248779296875
          ],
          [
            293.59912109375,
            293.60186767578125,
            293.5936279296875,
            293.60302734375
          ]
        ],
        [
          [
            292.398681640625,
            292.4869384765625,
            292.74945068359375,
            292.8670349121094
          ],
          [
            292.5869445800781,
            292.5303039550781,
            292.3885192871094,
            292.3748474121094
          ]
        ]
      ]
    },
    "u10": {
      "data": [
        [
          [
            3.450676918029785,
            3.29091739654541,
            3.10048770904541,
            2.50203800201416
          ],
          [
            3.56276798248291,
            3.334649085998535,
            3.061211585998535,
            2.513176918029785
          ]
        ],
        [
          [
            5.0031328201293945,
            5.009186744689941,
            5.107232093811035,
            5.183014869689941
          ],
          [
            5.141411781311035,
            5.066998481750488,
            5.0285234451293945,
            4.981255531311035
          ]
        ],
        [
          [
            4.379894256591797,
            4.211147308349609,
            3.972270965576172,
            3.9021568298339844
          ],
          [
            3.815044403076172,
            3.6205101013183594,
            3.4714927673339844,
            3.4734458923339844
          ]
        ]
      ]
    },
    "v10": {
      "data": [
        [
          [
            4.880218505859375,
            4.68743896484375,
            4.436065673828125,
            4.027069091796875
          ],
          [
            4.598968505859375,
            4.3682861328125,
            4.074554443359375,
            3.688018798828125
          ]
        ],
        [
          [
            3.798675537109375,
            3.8350067138671875,
            3.9512176513671875,
            4.039497375488281
          ],
          [
            3.8527755737304688,
            3.7904739379882812,
            3.7141036987304688,
            3.656097412109375
          ]
        ],
        [
          [
            0.71360182762146,
            0.98703932762146,
            1.18314528465271,
            1.63175368309021
          ],
          [
            0.76163649559021,
            1.21341872215271,
            1.67942214012146,
            2.240548849105835
          ]
        ]
      ]
    },
    "sp": {
      "data": [
        [
          [
            100783.421875,
            100853.21875,
            101041.21875,
            101183.8203125
          ],
          [
            100874.015625,
            100865.6171875,
            100805.6171875,
            100861.21875
          ]
        ],
        [
          [
            100806.1171875,
            100867.515625,
            101044.1171875,
            101177.3203125
          ],
          [
            100888.921875,
            100875.921875,
            100811.3203125,
            100861.1171875
          ]
        ],
        [
          [
            100843.625,
            100891.828125,
            101054.625,
            101173.625
          ],
          [
            100916.4296875,
            100890.4296875,
            100815.0234375,
            100856.4296875
          ]
        ]
      ]
    }
  },
  "pollution": {
    "pm25": 53,
    "pm10": 21,
    "o3": 27,
    "no2": 43,
    "so2": 4,
    "co": 4
  }
}