{
  "coords": {
    "number": {
      "data": 0
    },
    "valid_time": {
      "data": [
        "2019-04-03T08:00:00",
        "2019-04-03T12:00:00",
        "2019-04-03T18:00:00"
      ]
    },
    "latitude": {
      "data": [
        51.55,
        51.3
      ]
    },
    "longitude": {
      "data": [
        -0.5,
        -0.25,
        0.0,
        0.25
      ]
    },
    "expver": {
      "data": [
        "0001",
        "0001",
        "0001"
      ]
    }
  },
  "data_vars": {
    "tp": {
      "data": [
        [
          [
            0.0,
            0.0,
            0.0,
            0.0
          ],
          [
            0.0,
            0.0,
            0.0,
            0.0
          ]
        ],
        [
          [
            0.00016994438192341477,
            0.00014991722127888352,
            7.629430911038071e-05,
            0.00012359618267510086
          ],
          [
            9.28886147448793e-05,
            8.773840090725571e-05,
            6.351470074150711e-05,
            0.00017814560851547867
          ]
        ],
        [
          [
            9.594261064194143e-05,
            4.96894062962383e-05,
            6.761550321243703e-05,
            0.0002941131533589214
          ],
          [
            0.00011567919864319265,
            4.691779031418264e-05,
            4.043578519485891e-05,
            0.00034036635770462453
          ]
        ]
      ]
    },
    "t2m": {
      "data": [
        [
          [
            275.2177734375,
            275.41229248046875,
            275.74005126953125,
            276.1275329589844
          ],
          [
            275.29864501953125,
            275.4951171875,
            275.7349548339844,
            276.1451110839844
          ]
        ],
        [
          [
            279.6629333496094,
            279.6867370605469,
            279.8144836425781,
            279.6715087890625
          ],
          [
            279.7500305175781,
            279.7652587890625,
            279.7929992675781,
            279.79925537109375
          ]
        ],
        [
          [
            278.01605224609375,
            278.2164306640625,
            278.3312683105469,
            278.2121276855469
          ],
          [
            277.955078125,
            278.107421875,
            278.09063720703125,
            277.744140625
          ]
        ]
      ]
    },
    "u10": {
      "data": [
        [
          [
            1.4346253871917725,
            1.4225099086761475,
            1.395761251449585,
            1.145761251449585
          ],
          [
            1.2045533657073975,
            1.1674439907073975,
            1.08481764793396,
            0.7949768900871277
          ]
        ],
        [
          [
            0.9083266854286194,
            1.055009365081787,
            1.1362547874450684,
            0.8600860238075256
          ],
          [
            0.9889922738075256,
            1.1276640892028809,
            1.1591124534606934,
            0.8122344613075256
          ]
        ],
        [
          [
            0.6784055233001709,
            0.5844724178314209,
            0.0971677303314209,
            0.5032346248626709
          ],
          [
            1.201080083847046,
            1.267669439315796,
            1.205749273300171,
            1.365722417831421
          ]
        ]
      ]
    },
    "v10": {
      "data": [
        [
          [
            -1.9579925537109375,
            -1.6743927001953125,
            -1.446075439453125,
            -1.2015380859375
          ],
          [
            -2.0337677001953125,
            -1.7044677734375,
            -1.387481689453125,
            -1.193145751953125
          ]
        ],
        [
          [
            -0.6892150044441223,
            -0.6464446187019348,
            -0.6691039204597473,
            -0.5534728169441223
          ],
          [
            -0.9757445454597473,
            -0.8913634419441223,
            -0.7337554097175598,
            -0.3792632222175598
          ]
        ],
        [
          [
            2.331143379211426,
            2.4780092239379883,
            2.695004463195801,
            2.741482734680176
          ],
          [
            1.8287935256958008,
            1.9233217239379883,
            1.9696168899536133,
            1.8698091506958008
          ]
        ]
      ]
    },
    "sp": {
      "data": [
        [
          [
            99009.875,
            99054.4765625,
            99223.078125,
            99342.875
          ],
          [
            99060.4765625,
            99025.4765625,
            98937.6796875,
            98970.28125
          ]
        ],
        [
          [
            98916.3125,
            98968.3125,
            99143.9140625,
            99275.3125
          ],
          [
            98971.9140625,
            98944.7109375,
            98864.7109375,
            98909.3125
          ]
        ],
        [
          [
            98784.8984375,
            98845.8984375,
            99027.1015625,
            99154.8984375
          ],
          [
            98839.3046875,
            98823.8984375,
            98754.703125,
            98797.703125
          ]
        ]
      ]
    }
  },
  "pollution": {
    "pm25": 54,
    "pm10": 12,
    "o3": 23,
    "no2": 18,
    "so2": 2,
    "co": 10
  }
}