{
  "coords": {
    "number": {
      "data": 0
    },
    "valid_time": {
      "data": [
        "2020-11-07T08:00:00",
        "2020-11-07T12:00:00",
        "2020-11-07T18:00:00"
      ]
    },
    "latitude": {
      "data": [
        51.55,
        51.3
      ]
    },
    "longitude": {
      "data": [
        -0.5,
        -0.25,
        0.0,
        0.25
      ]
    },
    "expver": {
      "data": [
        "0001",
        "0001",
        "0001"
      ]
    }
  },
  "data_vars": {
    "tp": {
      "data": [
        [
          [
            0.0,
            0.0,
            0.0,
            0.0
          ],
          [
            0.0,
            0.0,
            0.0,
            0.0
          ]
        ],
        [
          [
            0.0,
            0.0,
            0.0,
            0.0
          ],
          [
            0.0,
            0.0,
            0.0,
            0.0
          ]
        ],
        [
          [
            0.0,
            0.0,
            0.0,
            0.0
          ],
          [
            0.0,
            0.0,
            0.0,
            0.0
          ]
        ]
      ]
    },
    "t2m": {
      "data": [
        [
          [
            277.6821594238281,
            277.83721923828125,
            278.07904052734375,
            278.6969909667969
          ],
          [
            278.4919128417969,
            278.6134033203125,
            278.7052001953125,
            278.7837219238281
          ]
        ],
        [
          [
            285.3412780761719,
            285.50262451171875,
            285.763916015625,
            285.5561218261719
          ],
          [
            286.08697509765625,
            286.15338134765625,
            286.1830749511719,
            286.01080322265625
          ]
        ],
        [
          [
            283.63372802734375,
            283.3587341308594,
            283.054443359375,
            283.0630187988281
          ],
          [
            284.083740234375,
            283.8196716308594,
            283.544677734375,
            283.2817687988281
          ]
        ]
      ]
    },
    "u10": {
      "data": [
        [
          [
            -2.5914955139160156,
            -2.4760780334472656,
            -2.297748565673828,
            -2.1055641174316406
          ],
          [
            -2.7979469299316406,
            -2.699512481689453,
            -2.599903106689453,
            -2.259082794189453
          ]
        ],
        [
          [
            -2.48081111907959,
            -2.33335018157959,
            -2.191351890563965,
            -2.1782751083374023
          ],
          [
            -2.68686580657959,
            -2.513434410095215,
            -2.33335018157959,
            -2.10092830657959
          ]
        ],
        [
          [
            -3.2373390197753906,
            -3.156475067138672,
            -2.9619483947753906,
            -2.873271942138672
          ],
          [
            -3.2060890197753906,
            -3.173084259033203,
            -3.1312828063964844,
            -2.8877296447753906
          ]
        ]
      ]
    },
    "v10": {
      "data": [
        [
          [
            0.3218017816543579,
            0.5239502191543579,
            0.6903625726699829,
            1.038781762123108
          ],
          [
            0.6704345941543579,
            0.9536377191543579,
            1.251489281654358,
            1.451684594154358
          ]
        ],
        [
          [
            0.7318809628486633,
            0.7111786007881165,
            0.7410610318183899,
            0.7465294003486633
          ],
          [
            0.8021934628486633,
            0.7705543637275696,
            0.771139919757843,
            0.7435997128486633
          ]
        ],
        [
          [
            -0.4321288466453552,
            -0.3776397109031677,
            -0.3129882216453552,
            -0.23271173238754272
          ],
          [
            -0.19950860738754272,
            -0.14365381002426147,
            -0.08349603414535522,
            -0.10322564840316772
          ]
        ]
      ]
    },
    "sp": {
      "data": [
        [
          [
            101135.59375,
            101206.59375,
            101397.390625,
            101538.59375
          ],
          [
            101155.7890625,
            101149.390625,
            101091.59375,
            101151.7890625
          ]
        ],
        [
          [
            101084.90625,
            101154.90625,
            101345.3046875,
            101491.3046875
          ],
          [
            101106.5078125,
            101100.703125,
            101043.703125,
            101105.703125
          ]
        ],
        [
          [
            101024.6171875,
            101098.6171875,
            101291.21875,
            101438.421875
          ],
          [
            101035.21875,
            101031.8203125,
            100977.6171875,
            101042.21875
          ]
        ]
      ]
    }
  },
  "pollution": {
    "pm25": 98,
    "pm10": 29,
    "o3": 2,
    "no2": 18,
    "so2": 4,
    "co": 7
  }
}