{
  "coords": {
    "number": {
      "data": 0
    },
    "valid_time": {
      "data": [
        "2022-01-18T08:00:00",
        "2022-01-18T12:00:00",
        "2022-01-18T18:00:00"
      ]
    },
    "latitude": {
      "data": [
        51.55,
        51.3
      ]
    },
    "longitude": {
      "data": [
        -0.5,
        -0.25,
        0.0,
        0.25
      ]
    },
    "expver": {
      "data": [
        "0001",
        "0001",
        "0001"
      ]
    }
  },
  "data_vars": {
    "tp": {
      "data": [
        [
          [
            0.0,
            0.0,
            0.0,
            0.0
          ],
          [
            0.0,
            0.0,
            0.0,
            0.0
          ]
        ],
        [
          [
            0.0,
            0.0,
            0.0,
            0.0
          ],
          [
            0.0,
            0.0,
            0.0,
            0.0
          ]
        ],
        [
          [
            1.6784859326435253e-05,
            1.7643073078943416e-05,
            1.9645882275654003e-05,
            1.4209751498128753e-05
          ],
          [
            4.196171175863128e-06,
            5.626682650472503e-06,
            6.866272997285705e-06,
            1.6689398762537166e-05
          ]
        ]
      ]
    },
    "t2m": {
      "data": [
        [
          [
            271.72027587890625,
            271.88629150390625,
            272.1710510253906,
            272.45074462890625
          ],
          [
            271.928466796875,
            272.043701171875,
            272.156982421875,
            272.3175354003906
          ]
        ],
        [
          [
            277.57135009765625,
            277.9076843261719,
            278.2596435546875,
            278.5639343261719
          ],
          [
            278.82525634765625,
            279.13739013671875,
            279.3440246582031,
            279.36041259765625
          ]
        ],
        [
          [
            277.30999755859375,
            277.4139099121094,
            277.68463134765625,
            277.5369567871094
          ],
          [
            277.3834228515625,
            277.2994384765625,
            277.1236572265625,
            276.8677978515625
          ]
        ]
      ]
    },
    "u10": {
      "data": [
        [
          [
            0.07693815231323242,
            0.11893033981323242,
            0.23807096481323242,
            0.4204745292663574
          ],
          [
            -0.6818509101867676,
            -0.7189602851867676,
            -0.7236599922180176,
            -0.4464993476867676
          ]
        ],
        [
          [
            0.3700319528579712,
            0.3610597848892212,
            0.3956209421157837,
            0.4415193796157837
          ],
          [
            -0.2567228078842163,
            -0.2848447561264038,
            -0.3004697561264038,
            -0.1942228078842163
          ]
        ],
        [
          [
            0.07421892881393433,
            0.013870418071746826,
            0.018554866313934326,
            -0.23202496767044067
          ],
          [
            -0.7460935711860657,
            -0.7943266034126282,
            -0.8105466961860657,
            -0.9187467694282532
          ]
        ]
      ]
    },
    "v10": {
      "data": [
        [
          [
            1.4415826797485352,
            1.5105218887329102,
            1.5788812637329102,
            1.7829828262329102
          ],
          [
            1.3671655654907227,
            1.4808435440063477,
            1.6755609512329102,
            1.9120874404907227
          ]
        ],
        [
          [
            2.279552459716797,
            2.3334617614746094,
            2.359050750732422,
            2.5020103454589844
          ],
          [
            2.7309226989746094,
            2.786968231201172,
            2.7914695739746094,
            2.8236961364746094
          ]
        ],
        [
          [
            -0.08721327781677246,
            0.17528367042541504,
            0.71962571144104,
            0.70009446144104
          ],
          [
            0.29384446144104004,
            0.46454453468322754,
            0.6428587436676025,
            0.5016539096832275
          ]
        ]
      ]
    },
    "sp": {
      "data": [
        [
          [
            102821.9609375,
            102889.359375,
            103080.9609375,
            103220.1640625
          ],
          [
            102869.359375,
            102855.7578125,
            102787.7578125,
            102841.1640625
          ]
        ],
        [
          [
            102810.8515625,
            102871.65625,
            103057.2578125,
            103193.65625
          ],
          [
            102854.0546875,
            102834.2578125,
            102760.2578125,
            102809.0546875
          ]
        ],
        [
          [
            102558.7421875,
            102614.3359375,
            102794.9375,
            102928.9375
          ],
          [
            102592.3359375,
            102567.5390625,
            102489.3359375,
            102536.9375
          ]
        ]
      ]
    }
  },
  "pollution": {
    "pm25": 100,
    "pm10": 31,
    "o3": 14,
    "no2": 22,
    "so2": 0,
    "co": 6
  }
}