{
  "coords": {
    "number": {
      "data": 0
    },
    "valid_time": {
      "data": [
        "2022-10-12T08:00:00",
        "2022-10-12T12:00:00",
        "2022-10-12T18:00:00"
      ]
    },
    "latitude": {
      "data": [
        51.55,
        51.3
      ]
    },
    "longitude": {
      "data": [
        -0.5,
        -0.25,
        0.0,
        0.25
      ]
    },
    "expver": {
      "data": [
        "0001",
        "0001",
        "0001"
      ]
    }
  },
  "data_vars": {
    "tp": {
      "data": [
        [
          [
            0.0,
            0.0,
            0.0,
            0.0
          ],
          [
            0.0,
            0.0,
            0.0,
            0.0
          ]
        ],
        [
          [
            0.0,
            2.0598992705345154e-05,
            0.00011596642434597015,
            2.0598992705345154e-05
          ],
          [
            0.0,
            5.150213837623596e-06,
            2.5939196348190308e-05,
            5.150213837623596e-06
          ]
        ],
        [
          [
            0.0,
            0.0,
            0.0,
            0.0
          ],
          [
            0.0,
            0.0,
            0.0,
            0.0
          ]
        ]
      ]
    },
    "t2m": {
      "data": [
        [
          [
            282.0950622558594,
            282.2220153808594,
            282.3724060058594,
            282.581787109375
          ],
          [
            282.1915283203125,
            282.363037109375,
            282.4934997558594,
            282.5884094238281
          ]
        ],
        [
          [
            288.8352355957031,
            288.83837890625,
            288.95281982421875,
            288.8660888671875
          ],
          [
            289.3536071777344,
            289.3125915527344,
            289.25164794921875,
            289.20672607421875
          ]
        ],
        [
          [
            287.26763916015625,
            287.08795166015625,
            286.962158203125,
            287.114501953125
          ],
          [
            287.1109619140625,
            286.8894958496094,
            286.6422119140625,
            286.831298828125
          ]
        ]
      ]
    },
    "u10": {
      "data": [
        [
          [
            -1.0960941314697266,
            -1.336526870727539,
            -1.6048831939697266,
            -1.6855411529541016
          ],
          [
            -1.4724674224853516,
            -1.694528579711914,
            -1.9007816314697266,
            -1.815042495727539
          ]
        ],
        [
          [
            1.7527008056640625,
            1.4323883056640625,
            1.07476806640625,
            1.28472900390625
          ],
          [
            1.432586669921875,
            1.123992919921875,
            0.8943023085594177,
            1.3614959716796875
          ]
        ],
        [
          [
            2.2520103454589844,
            2.0914573669433594,
            1.7836418151855469,
            1.7010307312011719
          ],
          [
            2.553569793701172,
            2.471538543701172,
            2.4102134704589844,
            2.2760276794433594
          ]
        ]
      ]
    },
    "v10": {
      "data": [
        [
          [
            3.2794885635375977,
            3.201165199279785,
            3.0675745010375977,
            2.981438636779785
          ],
          [
            2.8816308975219727,
            2.8097620010375977,
            2.7648401260375977,
            2.800774574279785
          ]
        ],
        [
          [
            4.420383453369141,
            4.392261505126953,
            4.373119354248047,
            4.471553802490234
          ],
          [
            4.435619354248047,
            4.335224151611328,
            4.208858489990234,
            4.221553802490234
          ]
        ],
        [
          [
            2.873394012451172,
            2.886676788330078,
            2.8927345275878906,
            3.0616798400878906
          ],
          [
            2.724956512451172,
            2.775737762451172,
            2.8823814392089844,
            3.039020538330078
          ]
        ]
      ]
    },
    "sp": {
      "data": [
        [
          [
            101190.0703125,
            101259.2734375,
            101450.671875,
            101597.2734375
          ],
          [
            101249.46875,
            101240.2734375,
            101181.0703125,
            101243.0703125
          ]
        ],
        [
          [
            101080.53125,
            101146.1328125,
            101329.734375,
            101472.9375
          ],
          [
            101140.734375,
            101130.1328125,
            101070.1328125,
            101133.1328125
          ]
        ],
        [
          [
            100854.125,
            100910.921875,
            101086.921875,
            101221.5234375
          ],
          [
            100938.125,
            100916.7265625,
            100844.7265625,
            100893.125
          ]
        ]
      ]
    }
  },
  "pollution": {
    "pm25": 54,
    "pm10": 28,
    "o3": 14,
    "no2": 30,
    "so2": 1,
    "co": 3
  }
}