{
  "coords": {
    "number": {
      "data": 0
    },
    "valid_time": {
      "data": [
        "2022-01-24T08:00:00",
        "2022-01-24T12:00:00",
        "2022-01-24T18:00:00"
      ]
    },
    "latitude": {
      "data": [
        51.55,
        51.3
      ]
    },
    "longitude": {
      "data": [
        -0.5,
        -0.25,
        0.0,
        0.25
      ]
    },
    "expver": {
      "data": [
        "0001",
        "0001",
        "0001"
      ]
    }
  },
  "data_vars": {
    "tp": {
      "data": [
        [
          [
            8.011051249923185e-06,
            1.2493041140260175e-05,
            1.1253450793446973e-05,
            8.678343874635175e-06
          ],
          [
            6.389618647517636e-06,
            1.544952465337701e-05,
            2.4318509531440213e-05,
            2.1362491679610685e-05
          ]
        ],
        [
          [
            0.0,
            0.0,
            0.0,
            0.0
          ],
          [
            0.0,
            0.0,
            0.0,
            0.0
          ]
        ],
        [
          [
            3.8146390579640865e-07,
            0.0,
            0.0,
            0.0
          ],
          [
            4.76837158203125e-07,
            0.0,
            0.0,
            0.0
          ]
        ]
      ]
    },
    "t2m": {
      "data": [
        [
          [
            276.9059753417969,
            276.86614990234375,
            276.7872314453125,
            276.8126220703125
          ],
          [
            277.1094970703125,
            277.0298156738281,
            276.8868408203125,
            276.85089111328125
          ]
        ],
        [
          [
            276.8468017578125,
            276.90777587890625,
            277.04058837890625,
            277.1565856933594
          ],
          [
            277.2745361328125,
            277.3038330078125,
            277.3077392578125,
            277.37884521484375
          ]
        ],
        [
          [
            276.5408020019531,
            276.3318176269531,
            276.2497863769531,
            276.40447998046875
          ],
          [
            276.6611328125,
            276.34979248046875,
            275.96307373046875,
            275.9169921875
          ]
        ]
      ]
    },
    "u10": {
      "data": [
        [
          [
            -1.6103057861328125,
            -1.578857421875,
            -1.5444793701171875,
            -1.408935546875
          ],
          [
            -1.9175262451171875,
            -1.8944854736328125,
            -1.8886260986328125,
            -1.730224609375
          ]
        ],
        [
          [
            -1.4885597229003906,
            -1.4346580505371094,
            -1.3563346862792969,
            -1.3612174987792969
          ],
          [
            -1.7504768371582031,
            -1.6918830871582031,
            -1.6284065246582031,
            -1.5670738220214844
          ]
        ],
        [
          [
            -0.8137121200561523,
            -0.8121557235717773,
            -0.9086370468139648,
            -0.9582433700561523
          ],
          [
            -0.9893026351928711,
            -0.9719152450561523,
            -1.047896385192871,
            -1.1254339218139648
          ]
        ]
      ]
    },
    "v10": {
      "data": [
        [
          [
            -0.16315609216690063,
            -0.06372982263565063,
            -0.032678186893463135,
            0.07552188634872437
          ],
          [
            -0.44205623865127563,
            -0.32369381189346313,
            -0.18757015466690063,
            -0.12564998865127563
          ]
        ],
        [
          [
            0.4678024649620056,
            0.43049854040145874,
            0.41194385290145874,
            0.48010867834091187
          ],
          [
            0.3566727042198181,
            0.3008102774620056,
            0.27210086584091187,
            0.3205398917198181
          ]
        ],
        [
          [
            -0.4527190327644348,
            -0.4281066060066223,
            -0.4421752095222473,
            -0.3228362202644348
          ],
          [
            -0.8236144185066223,
            -0.8154051899909973,
            -0.8124755024909973,
            -0.7892363667488098
          ]
        ]
      ]
    },
    "sp": {
      "data": [
        [
          [
            102334.171875,
            102397.7734375,
            102588.171875,
            102729.3671875
          ],
          [
            102365.7734375,
            102348.171875,
            102277.5703125,
            102330.5703125
          ]
        ],
        [
          [
            102397.5625,
            102458.359375,
            102646.5625,
            102785.1640625
          ],
          [
            102431.5625,
            102410.9609375,
            102335.9609375,
            102385.9609375
          ]
        ],
        [
          [
            102365.0859375,
            102425.6796875,
            102612.0859375,
            102751.484375
          ],
          [
            102399.6796875,
            102379.0859375,
            102303.6796875,
            102353.8828125
          ]
        ]
      ]
    }
  },
  "pollution": {
    "pm25": 73,
    "pm10": 28,
    "o3": 12,
    "no2": 19,
    "so2": 1,
    "co": 0
  }
}