{
  "coords": {
    "number": {
      "data": 0
    },
    "valid_time": {
      "data": [
        "2022-02-17T08:00:00",
        "2022-02-17T12:00:00",
        "2022-02-17T18:00:00"
      ]
    },
    "latitude": {
      "data": [
        51.55,
        51.3
      ]
    },
    "longitude": {
      "data": [
        -0.5,
        -0.25,
        0.0,
        0.25
      ]
    },
    "expver": {
      "data": [
        "0001",
        "0001",
        "0001"
      ]
    }
  },
  "data_vars": {
    "tp": {
      "data": [
        [
          [
            0.0,
            0.0,
            0.0,
            0.0
          ],
          [
            0.0,
            0.0,
            0.0,
            0.0
          ]
        ],
        [
          [
            0.0,
            0.0,
            0.0,
            0.0
          ],
          [
            0.0,
            0.0,
            0.0,
            0.0
          ]
        ],
        [
          [
            0.0,
            0.0,
            0.0,
            0.0
          ],
          [
            0.0,
            0.0,
            0.0,
            0.0
          ]
        ]
      ]
    },
    "t2m": {
      "data": [
        [
          [
            280.55413818359375,
            280.68109130859375,
            280.879150390625,
            280.9978942871094
          ],
          [
            280.94085693359375,
            281.035400390625,
            281.09320068359375,
            281.2232971191406
          ]
        ],
        [
          [
            283.267578125,
            283.22027587890625,
            283.2917785644531,
            283.21795654296875
          ],
          [
            283.6628723144531,
            283.5296630859375,
            283.37615966796875,
            283.3046875
          ]
        ],
        [
          [
            281.7054748535156,
            281.76641845703125,
            281.9058532714844,
            281.9468688964844
          ],
          [
            281.8695373535156,
            281.9097595214844,
            281.93243408203125,
            281.9761657714844
          ]
        ]
      ]
    },
    "u10": {
      "data": [
        [
          [
            6.651947975158691,
            6.617768287658691,
            6.569329261779785,
            6.901749610900879
          ],
          [
            6.830269813537598,
            6.797257423400879,
            6.814835548400879,
            6.949799537658691
          ]
        ],
        [
          [
            5.84090518951416,
            6.213189125061035,
            6.79171085357666,
            7.57979679107666
          ],
          [
            5.68642520904541,
            5.932915687561035,
            6.307915687561035,
            6.89620304107666
          ]
        ],
        [
          [
            5.390737533569336,
            5.507162094116211,
            5.606557846069336,
            5.963003158569336
          ],
          [
            4.705007553100586,
            4.840749740600586,
            5.110464096069336,
            5.425893783569336
          ]
        ]
      ]
    },
    "v10": {
      "data": [
        [
          [
            0.3372863531112671,
            0.4700988531112671,
            0.6093581914901733,
            0.7743972539901733
          ],
          [
            0.2835754156112671,
            0.37986600399017334,
            0.4181426763534546,
            0.49880826473236084
          ]
        ],
        [
          [
            1.406265377998352,
            1.044357419013977,
            0.635574460029602,
            0.33714306354522705
          ],
          [
            0.917801022529602,
            0.528335690498352,
            0.09962475299835205,
            -0.17204272747039795
          ]
        ],
        [
          [
            0.6478927731513977,
            0.6000412106513977,
            0.5047271847724915,
            0.5398834347724915
          ],
          [
            0.6750381588935852,
            0.6127365231513977,
            0.5162513852119446,
            0.48031312227249146
          ]
        ]
      ]
    },
    "sp": {
      "data": [
        [
          [
            99800.109375,
            99843.5078125,
            100007.703125,
            100120.109375
          ],
          [
            99912.3046875,
            99878.90625,
            99792.703125,
            99819.109375
          ]
        ],
        [
          [
            100098.0234375,
            100157.8203125,
            100335.2265625,
            100455.421875
          ],
          [
            100226.2265625,
            100209.8203125,
            100137.421875,
            100171.8203125
          ]
        ],
        [
          [
            100152.6171875,
            100200.015625,
            100369.4140625,
            100491.8203125
          ],
          [
            100255.8203125,
            100225.421875,
            100143.421875,
            100179.015625
          ]
        ]
      ]
    }
  },
  "pollution": {
    "pm25": 49,
    "pm10": 26,
    "o3": 31,
    "no2": 15,
    "so2": 0,
    "co": 6
  }
}