{
  "coords": {
    "number": {
      "data": 0
    },
    "valid_time": {
      "data": [
        "2023-02-02T08:00:00",
        "2023-02-02T12:00:00",
        "2023-02-02T18:00:00"
      ]
    },
    "latitude": {
      "data": [
        51.55,
        51.3
      ]
    },
    "longitude": {
      "data": [
        -0.5,
        -0.25,
        0.0,
        0.25
      ]
    },
    "expver": {
      "data": [
        "0001",
        "0001",
        "0001"
      ]
    }
  },
  "data_vars": {
    "tp": {
      "data": [
        [
          [
            0.0,
            0.0,
            0.0,
            0.0
          ],
          [
            0.0,
            0.0,
            0.0,
            0.0
          ]
        ],
        [
          [
            7.3433848228887655e-06,
            1.6213389244512655e-06,
            1.6213389244512655e-06,
            2.2888643798069097e-06
          ],
          [
            1.4400481632037554e-05,
            7.247924258990679e-06,
            1.525878360553179e-06,
            2.002715518756304e-06
          ]
        ],
        [
          [
            0.0,
            0.0,
            0.0,
            0.0
          ],
          [
            0.0,
            0.0,
            0.0,
            0.0
          ]
        ]
      ]
    },
    "t2m": {
      "data": [
        [
          [
            279.2989501953125,
            279.05517578125,
            278.94384765625,
            279.04583740234375
          ],
          [
            279.3438720703125,
            279.01458740234375,
            278.73175048828125,
            278.72979736328125
          ]
        ],
        [
          [
            283.50225830078125,
            283.4971618652344,
            283.5682373046875,
            283.4783935546875
          ],
          [
            283.6951904296875,
            283.61981201171875,
            283.48858642578125,
            283.35614013671875
          ]
        ],
        [
          [
            282.7216491699219,
            282.6790771484375,
            282.6357116699219,
            282.71893310546875
          ],
          [
            282.75640869140625,
            282.7372741699219,
            282.6833801269531,
            282.7243957519531
          ]
        ]
      ]
    },
    "u10": {
      "data": [
        [
          [
            4.666433334350586,
            4.481267929077148,
            4.237524032592773,
            4.414678573608398
          ],
          [
            4.363500595092773,
            4.177373886108398,
            4.050024032592773,
            4.207448959350586
          ]
        ],
        [
          [
            6.792011260986328,
            6.773067474365234,
            6.708423614501953,
            6.935962677001953
          ],
          [
            6.784397125244141,
            6.705684661865234,
            6.619747161865234,
            6.732051849365234
          ]
        ],
        [
          [
            5.180503845214844,
            5.007652282714844,
            4.804725646972656,
            5.0392913818359375
          ],
          [
            4.995933532714844,
            4.8322601318359375,
            4.76605224609375,
            4.9445648193359375
          ]
        ]
      ]
    },
    "v10": {
      "data": [
        [
          [
            0.8913664817810059,
            0.9663634300231934,
            1.1120696067810059,
            1.2187132835388184
          ],
          [
            1.045274257659912,
            1.1132445335388184,
            1.1456618309020996,
            1.1345305442810059
          ]
        ],
        [
          [
            0.5541839599609375,
            0.616485595703125,
            0.8096542358398438,
            1.02703857421875
          ],
          [
            0.6840667724609375,
            0.7241058349609375,
            0.75555419921875,
            0.87567138671875
          ]
        ],
        [
          [
            2.216250419616699,
            2.256289482116699,
            2.2697629928588867,
            2.2959394454956055
          ],
          [
            2.036562919616699,
            2.0676145553588867,
            2.0576581954956055,
            2.0451536178588867
          ]
        ]
      ]
    },
    "sp": {
      "data": [
        [
          [
            101700.4765625,
            101749.4765625,
            101921.875,
            102045.28125
          ],
          [
            101804.4765625,
            101774.4765625,
            101692.28125,
            101725.6796875
          ]
        ],
        [
          [
            101759.1796875,
            101809.7734375,
            101982.1796875,
            102101.375
          ],
          [
            101870.578125,
            101841.7734375,
            101760.375,
            101792.1796875
          ]
        ],
        [
          [
            101746.796875,
            101798.59375,
            101972.0,
            102096.3984375
          ],
          [
            101867.59375,
            101842.1953125,
            101764.1953125,
            101800.1953125
          ]
        ]
      ]
    }
  },
  "pollution": {
    "pm25": 47,
    "pm10": 26,
    "o3": 23,
    "no2": 19,
    "so2": 0,
    "co": 3
  }
}