{
  "coords": {
    "number": {
      "data": 0
    },
    "valid_time": {
      "data": [
        "2023-01-02T08:00:00",
        "2023-01-02T12:00:00",
        "2023-01-02T18:00:00"
      ]
    },
    "latitude": {
      "data": [
        51.55,
        51.3
      ]
    },
    "longitude": {
      "data": [
        -0.5,
        -0.25,
        0.0,
        0.25
      ]
    },
    "expver": {
      "data": [
        "0001",
        "0001",
        "0001"
      ]
    }
  },
  "data_vars": {
    "tp": {
      "data": [
        [
          [
            1.3351436791708693e-06,
            5.340762072592042e-06,
            7.152184480219148e-06,
            1.1539645129232667e-05
          ],
          [
            1.2111477190046571e-05,
            1.8119439118891023e-05,
            2.3841485017328523e-05,
            3.852844383800402e-05
          ]
        ],
        [
          [
            5.626493475574534e-06,
            8.487516424793284e-06,
            4.195982000965159e-06,
            1.277905084862141e-05
          ],
          [
            2.0027173377457075e-06,
            8.392521522182506e-06,
            1.6212372429436073e-05,
            2.7656464226311073e-05
          ]
        ],
        [
          [
            0.0,
            0.0,
            0.0,
            0.0
          ],
          [
            0.0,
            0.0,
            0.0,
            0.0
          ]
        ]
      ]
    },
    "t2m": {
      "data": [
        [
          [
            278.52667236328125,
            278.77630615234375,
            278.9966125488281,
            279.3630065917969
          ],
          [
            278.8286437988281,
            279.0798034667969,
            279.2755126953125,
            279.5841064453125
          ]
        ],
        [
          [
            280.4068603515625,
            280.5689697265625,
            280.83184814453125,
            280.9888916015625
          ],
          [
            280.8810729980469,
            280.9818420410156,
            281.0580139160156,
            281.21856689453125
          ]
        ],
        [
          [
            277.18060302734375,
            277.2594909667969,
            277.25909423828125,
            277.20050048828125
          ],
          [
            276.70989990234375,
            276.8188781738281,
            276.91693115234375,
            276.9653625488281
          ]
        ]
      ]
    },
    "u10": {
      "data": [
        [
          [
            3.182239532470703,
            3.129314422607422,
            3.0548973083496094,
            3.195911407470703
          ],
          [
            2.931072235107422,
            2.8547019958496094,
            2.8884925842285156,
            2.960559844970703
          ]
        ],
        [
          [
            2.7126474380493164,
            2.7614755630493164,
            2.8347177505493164,
            3.1054162979125977
          ],
          [
            2.68862247467041,
            2.711472511291504,
            2.761277198791504,
            2.9153833389282227
          ]
        ],
        [
          [
            1.4769744873046875,
            1.5601806640625,
            1.6422119140625,
            1.8244476318359375
          ],
          [
            1.2957305908203125,
            1.3845977783203125,
            1.5320587158203125,
            1.638702392578125
          ]
        ]
      ]
    },
    "v10": {
      "data": [
        [
          [
            0.4967496991157532,
            0.7573087811470032,
            0.9463651776313782,
            1.3032071590423584
          ],
          [
            0.8990934491157532,
            1.1555325984954834,
            1.3951871395111084,
            1.6604154109954834
          ]
        ],
        [
          [
            -0.8239154815673828,
            -0.9073123931884766,
            -1.011026382446289,
            -1.1041889190673828
          ],
          [
            -1.0092639923095703,
            -1.0825061798095703,
            -1.1133670806884766,
            -1.0739154815673828
          ]
        ],
        [
          [
            1.6159906387329102,
            1.5232172012329102,
            1.4046564102172852,
            1.2048578262329102
          ],
          [
            1.3575830459594727,
            1.2941064834594727,
            1.2337579727172852,
            1.0689172744750977
          ]
        ]
      ]
    },
    "sp": {
      "data": [
        [
          [
            100395.296875,
            100444.8984375,
            100616.4921875,
            100741.4921875
          ],
          [
            100460.6953125,
            100432.4921875,
            100354.09375,
            100395.8984375
          ]
        ],
        [
          [
            100805.78125,
            100850.1796875,
            101018.78125,
            101137.9765625
          ],
          [
            100865.9765625,
            100831.78125,
            100745.578125,
            100778.1796875
          ]
        ],
        [
          [
            101228.6015625,
            101290.0078125,
            101474.6015625,
            101609.0078125
          ],
          [
            101294.0078125,
            101276.0078125,
            101205.8046875,
            101253.40625
          ]
        ]
      ]
    }
  },
  "pollution": {
    "pm25": 48,
    "pm10": 13,
    "o3": 28,
    "no2": 18,
    "so2": 1,
    "co": 3
  }
}